api_biubiu/__init__.py
api_biubiu/api_biubiu.py
ApiBiuBiu-0.0.2.dist-info/LICENSE
ApiBiuBiu-0.0.2.dist-info/METADATA
ApiBiuBiu-0.0.2.dist-info/WHEEL
ApiBiuBiu-0.0.2.dist-info/top_level.txt
ApiBiuBiu-0.0.2.dist-info/RECORD
