Metadata-Version: 2.1
Name: ApiBiuBiu
Version: 0.0.2
Summary: unittestAndMultiprocessing
Home-page: https://gitee.com/jpf999/unittest_report
Author: 满眼乱世妖娆
Author-email: 597038837@qq.com
License: MIT
Platform: UNKNOWN
Classifier: Topic :: Games/Entertainment 
Classifier: Topic :: Games/Entertainment :: Puzzle Games
Classifier: Topic :: Games/Entertainment :: Board Games
Classifier: Topic :: Software Development :: Libraries :: Python Modules
Classifier: Programming Language :: Python
Classifier: Programming Language :: Python :: 3
Classifier: Programming Language :: Python :: 3.5
Classifier: Programming Language :: Python :: 3.5
Classifier: Programming Language :: Python :: 3.6
Classifier: Programming Language :: Python :: 3.7
Classifier: Programming Language :: Python :: Implementation :: CPython
